LICENSE
pyproject.toml
eo_tides/__init__.py
eo_tides/eo.py
eo_tides/model.py
eo_tides/stac.py
eo_tides/stats.py
eo_tides/utils.py
eo_tides/validation.py
eo_tides-0.10.2.dist-info/METADATA
eo_tides-0.10.2.dist-info/WHEEL
eo_tides-0.10.2.dist-info/licenses/LICENSE
eo_tides-0.10.2.dist-info/RECORD
