Metadata-Version: 2.4
Name: eo-tides
Version: 0.10.2
Summary: Tide modelling tools for large-scale satellite earth observation analysis
Project-URL: Homepage, https://GeoscienceAustralia.github.io/eo-tides/
Project-URL: Repository, https://github.com/GeoscienceAustralia/eo-tides
Project-URL: Documentation, https://GeoscienceAustralia.github.io/eo-tides/
Author: Robbi Bishop-Taylor, Stephen Sagar, Claire Phillips, Vanessa Newey
Author-email: Robbi.BishopTaylor@ga.gov.au
License-File: LICENSE
Keywords: coastal analysis,earth observation,oceanography,remote sensing,satellite data,tide modeling,tide modelling
Classifier: Development Status :: 3 - Alpha
Classifier: Intended Audience :: Science/Research
Classifier: License :: OSI Approved :: Apache Software License
Classifier: Programming Language :: Python :: 3.10
Classifier: Programming Language :: Python :: 3.11
Classifier: Programming Language :: Python :: 3.12
Classifier: Programming Language :: Python :: 3.13
Classifier: Topic :: Scientific/Engineering
Classifier: Topic :: Scientific/Engineering :: GIS
Classifier: Topic :: Scientific/Engineering :: Image Processing
Classifier: Topic :: Scientific/Engineering :: Oceanography
Classifier: Topic :: Scientific/Engineering :: Visualization
Requires-Python: <4.0,>=3.10
Requires-Dist: colorama>=0.4.3
Requires-Dist: dask[complete]>=2023.1.0
Requires-Dist: geopandas>=0.10.0
Requires-Dist: matplotlib>=3.8.0
Requires-Dist: numpy>=1.26.0
Requires-Dist: odc-geo>=0.4.7
Requires-Dist: odc-stac[botocore]>=0.3.10
Requires-Dist: pandas>=2.2.0
Requires-Dist: planetary-computer>=1.0.0
Requires-Dist: psutil>=5.8.0
Requires-Dist: pyogrio>=0.10.0
Requires-Dist: pyproj>=3.7.0
Requires-Dist: pystac-client>=0.8.3
Requires-Dist: pytmd<3.0.0,>=2.2.8
Requires-Dist: scikit-learn>=1.4.0
Requires-Dist: scipy>=1.14.1
Requires-Dist: shapely>=2.0.6
Requires-Dist: timescale>=0.0.3
Requires-Dist: tqdm>=4.55.0
Requires-Dist: xarray>=2022.3.0
Provides-Extra: notebooks
Requires-Dist: folium>=0.16.0; extra == 'notebooks'
Requires-Dist: jupyter>=1.0.0; extra == 'notebooks'
